<?xml version="1.0" ?>

<server xmlns="urn:jboss:domain:2.2">

    <extensions>
        <extension module="org.jboss.as.clustering.infinispan"/>
        <extension module="org.jboss.as.connector"/>
        <extension module="org.jboss.as.deployment-scanner"/>
        <extension module="org.jboss.as.ee"/>
        <extension module="org.jboss.as.ejb3"/>
        <extension module="org.jboss.as.jaxrs"/>
        <extension module="org.jboss.as.jdr"/>
        <extension module="org.jboss.as.jmx"/>
        <extension module="org.jboss.as.jpa"/>
        <extension module="org.jboss.as.jsf"/>
        <extension module="org.jboss.as.logging"/>
        <extension module="org.jboss.as.mail"/>
        <extension module="org.jboss.as.naming"/>
        <extension module="org.jboss.as.pojo"/>
        <extension module="org.jboss.as.remoting"/>
        <extension module="org.jboss.as.sar"/>
        <extension module="org.jboss.as.security"/>
        <extension module="org.jboss.as.transactions"/>
        <extension module="org.jboss.as.webservices"/>
        <extension module="org.jboss.as.weld"/>
        <extension module="org.wildfly.extension.batch"/>
        <extension module="org.wildfly.extension.io"/>
        <extension module="org.wildfly.extension.undertow"/>
    </extensions>

    <system-properties>
        <property name="idol.config_dir" value="applconf/idol_config"/>
    </system-properties>

    <interfaces>
        <interface name="management">
            <any-ipv4-address/>
        </interface>
        <interface name="public">
            <any-ipv4-address/>
        </interface>
        <interface name="unsecure">
            <any-ipv4-address/>
        </interface>
    </interfaces>

</server>
